cellannotation/__init__.py
cellannotation/annotate_samples.py
cellannotation/utils.py
cellannotation/tests/__init__.py
cellannotation/tests/test_annotate_samples.py
cellannotation-0.1.0.dist-info/LICENSE
cellannotation-0.1.0.dist-info/METADATA
cellannotation-0.1.0.dist-info/WHEEL
cellannotation-0.1.0.dist-info/top_level.txt
cellannotation-0.1.0.dist-info/RECORD
