Metadata-Version: 2.1
Name: cellannotation
Version: 0.1.0
Summary: Package for annotating the data (e.g. cell data).
Home-page: http://biolab.si/
Author: Bioinformatics Laboratory, FRI UL
Author-email: contact@orange.biolab.si
License: UNKNOWN
Keywords: cells,annotation
Platform: UNKNOWN
Classifier: Programming Language :: Python
Classifier: License :: OSI Approved :: MIT License
Classifier: Operating System :: OS Independent
Classifier: Development Status :: 4 - Beta
Requires-Dist: numpy
Requires-Dist: pandas
Requires-Dist: scipy
